neucore/__init__.py
neucore/env.py
neucore/uploadUtils.py
neucore-1.0.7.dist-info/LICENSE
neucore-1.0.7.dist-info/METADATA
neucore-1.0.7.dist-info/WHEEL
neucore-1.0.7.dist-info/top_level.txt
neucore-1.0.7.dist-info/RECORD
