Metadata-Version: 2.1
Name: neucore
Version: 1.0.7
Summary: A package for Ailiverse AI models
Home-page: https://ailiverse.com
Author: Nicholas Chua, Burhan Ul Tayyab
Author-email: Nicholas Chua <nicholas@ailiverse.com>, Burhan Ul Tayyab <burhanultayyab@ailiverse.com>
Project-URL: Homepage, https://github.com/ailiverse/neucore
Project-URL: Bug Tracker, https://github.com/ailiverse/neucore/issues
Classifier: Programming Language :: Python :: 3
Classifier: License :: OSI Approved :: MIT License
Classifier: Operating System :: OS Independent
Requires-Python: >=3.5
License-File: LICENSE
Requires-Dist: requests
Requires-Dist: tqdm
Requires-Dist: yaspin
Requires-Dist: requests-toolbelt
